HISTORY.rst
LICENSE
MANIFEST.in
README.rst
setup.py
django_kronos.egg-info/PKG-INFO
django_kronos.egg-info/SOURCES.txt
django_kronos.egg-info/dependency_links.txt
django_kronos.egg-info/not-zip-safe
django_kronos.egg-info/requires.txt
django_kronos.egg-info/top_level.txt
kronos/__init__.py
kronos/__init__.pyc
kronos/settings.py
kronos/settings.pyc
kronos/settings_test.py
kronos/settings_test.pyc
kronos/utils.pyc
kronos/version.py
kronos/version.pyc
kronos/management/__init__.py
kronos/management/__init__.pyc
kronos/management/commands/__init__.py
kronos/management/commands/__init__.pyc
kronos/management/commands/installtasks.py
kronos/management/commands/installtasks.pyc
kronos/management/commands/runtask.py
kronos/management/commands/runtask.pyc
kronos/management/commands/showtasks.py
kronos/management/commands/showtasks.pyc
kronos/management/commands/uninstalltasks.py
kronos/management/commands/uninstalltasks.pyc
kronos/tests/__init__.py
kronos/tests/__init__.pyc
kronos/tests/tests.py
kronos/tests/tests.pyc
kronos/tests/project/__init__.py
kronos/tests/project/__init__.pyc
kronos/tests/project/cron.py
kronos/tests/project/cron.pyc
kronos/tests/project/app/__init__.py
kronos/tests/project/app/__init__.pyc
kronos/tests/project/app/cron.py
kronos/tests/project/app/cron.pyc
kronos/tests/project/app/management/__init__.py
kronos/tests/project/app/management/__init__.pyc
kronos/tests/project/app/management/commands/__init__.py
kronos/tests/project/app/management/commands/__init__.pyc
kronos/tests/project/app/management/commands/task.py
kronos/tests/project/app/management/commands/task.pyc
kronos/tests/project/app/management/commands/task_with_args.py
kronos/tests/project/app/management/commands/task_with_args.pyc
kronos/tests/project/app/management/commands/task_with_empty_args.py
kronos/tests/project/app/management/commands/task_with_empty_args.pyc